folstools/__init__.py
folstools/aes.py
folstools/googleapi.py
folstools/mydriver.py
folstools/mygist.py
folstools/myrequests.py
folstools/myutils.py
folstools/orglab/__init__.py
folstools/orglab/googledoc.py
folstools/orglab/release.py
folstools/orglab/xf.py
folstools/qt/__init__.py
folstools/qt/betinfo.py
folstools/qt/captcha.py
folstools/qt/utils.py
folstools/tk/widgets.py
folstools/win32/__init__.py
folstools/win32/utils.py
folstools-0.0.1.dist-info/DESCRIPTION.rst
folstools-0.0.1.dist-info/METADATA
folstools-0.0.1.dist-info/RECORD
folstools-0.0.1.dist-info/WHEEL
folstools-0.0.1.dist-info/metadata.json
folstools-0.0.1.dist-info/top_level.txt
